{"canUnlink": false, "_id": "1069296", "node": {"_id": "6908", "description": "<p><strong>EN<br></strong> Provide advice on solutions for structured an unstructured data.</p>\r\n<p><strong> NL<br></strong> Adviseren in oplossingen voor gestructureerde en ongestructureerde data.</p>", "title": "Advise-O3.3", "displayName": "", "calculationMethod": "decaying_average", "calculationInt": 65, "masteryPoints": 3.0, "ratings": [{"description": "Outstanding", "points": 5.0, "__typename": "ProficiencyRating"}, {"description": "Good", "points": 4.0, "__typename": "ProficiencyRating"}, {"description": "Satisfactory", "points": 3.0, "__typename": "ProficiencyRating"}, {"description": "Unsatisfactory", "points": 0.0, "__typename": "ProficiencyRating"}], "canEdit": false, "canArchive": false, "contextType": "Account", "contextId": "1", "friendlyDescription": null, "__typename": "LearningOutcome"}, "group": {"_id": "57789", "title": "Level 3", "__typename": "LearningOutcomeGroup"}, "__typename": "ContentTag"}